dictionary/__init__.py
dictionary/dictionary.py
ci_cd_elhamin-2.0.1.dist-info/METADATA
ci_cd_elhamin-2.0.1.dist-info/WHEEL
ci_cd_elhamin-2.0.1.dist-info/top_level.txt
ci_cd_elhamin-2.0.1.dist-info/RECORD
